{
  "level_index": 26,
  "gravity": 12,
  "fuel": 195,
  "oxygen": 45,
  "palette": [
    [
      0,
      0,
      0
    ],
    [
      28,
      28,
      28
    ],
    [
      0,
      141,
      0
    ],
    [
      48,
      48,
      48
    ],
    [
      68,
      68,
      68
    ],
    [
      89,
      89,
      89
    ],
    [
      113,
      113,
      113
    ],
    [
      133,
      133,
      133
    ],
    [
      80,
      80,
      80
    ],
    [
      68,
      68,
      214
    ],
    [
      68,
      214,
      68
    ],
    [
      153,
      153,
      153
    ],
    [
      214,
      68,
      68
    ],
    [
      174,
      174,
      174
    ],
    [
      194,
      194,
      194
    ],
    [
      214,
      214,
      214
    ],
    [
      20,
      20,
      20
    ],
    [
      0,
      117,
      0
    ],
    [
      36,
      36,
      36
    ],
    [
      56,
      56,
      56
    ],
    [
      72,
      72,
      72
    ],
    [
      93,
      93,
      93
    ],
    [
      109,
      109,
      109
    ],
    [
      64,
      64,
      64
    ],
    [
      56,
      56,
      174
    ],
    [
      56,
      174,
      56
    ],
    [
      125,
      125,
      125
    ],
    [
      174,
      56,
      56
    ],
    [
      141,
      141,
      141
    ],
    [
      157,
      157,
      157
    ],
    [
      174,
      174,
      174
    ],
    [
      20,
      20,
      20
    ],
    [
      0,
      101,
      0
    ],
    [
      32,
      32,
      32
    ],
    [
      48,
      48,
      48
    ],
    [
      60,
      60,
      60
    ],
    [
      80,
      80,
      80
    ],
    [
      93,
      93,
      93
    ],
    [
      56,
      56,
      56
    ],
    [
      48,
      48,
      153
    ],
    [
      48,
      153,
      48
    ],
    [
      109,
      109,
      109
    ],
    [
      153,
      48,
      48
    ],
    [
      121,
      121,
      121
    ],
    [
      137,
      137,
      137
    ],
    [
      153,
      153,
      153
    ],
    [
      16,
      16,
      16
    ],
    [
      0,
      85,
      0
    ],
    [
      28,
      28,
      28
    ],
    [
      40,
      40,
      40
    ],
    [
      52,
      52,
      52
    ],
    [
      64,
      64,
      64
    ],
    [
      76,
      76,
      76
    ],
    [
      48,
      48,
      48
    ],
    [
      40,
      40,
      125
    ],
    [
      40,
      125,
      40
    ],
    [
      89,
      89,
      89
    ],
    [
      125,
      40,
      40
    ],
    [
      101,
      101,
      101
    ],
    [
      113,
      113,
      113
    ],
    [
      125,
      125,
      125
    ],
    [
      214,
      214,
      214
    ],
    [
      174,
      174,
      174
    ],
    [
      153,
      153,
      153
    ],
    [
      125,
      125,
      125
    ],
    [
      125,
      125,
      125
    ],
    [
      80,
      117,
      93
    ],
    [
      60,
      85,
      64
    ],
    [
      101,
      145,
      113
    ],
    [
      97,
      137,
      105
    ],
    [
      80,
      117,
      89
    ],
    [
      60,
      85,
      64
    ]
  ],
  "rows": [
    [
      null,
      null,
      null,
      {
        "val": 1,
        "full": false,
        "half": false,
        "tunnel": false,
        "top_color": 0,
        "bottom_color": 1,
        "low3": 1
      },
      null,
      null,
      null
    ],
    [
      null,
      null,
      null,
      {
        "val": 1,
        "full": false,
        "half": false,
        "tunnel": false,
        "top_color": 0,
        "bottom_color": 1,
        "low3": 1
      },
      null,
      null,
      null
    ],
    [
      null,
      null,
      null,
      {
        "val": 1,
        "full": false,
        "half": false,
        "tunnel": false,
        "top_color": 0,
        "bottom_color": 1,
        "low3": 1
      },
      null,
      null,
      null
    ],
    [
      null,
      null,
      null,
      {
        "val": 3,
        "full": false,
        "half": false,
        "tunnel": false,
        "top_color": 0,
        "bottom_color": 3,
        "low3": 3
      },
      null,
      null,
      null
    ],
    [
      null,
      null,
      null,
      {
        "val": 4,
        "full": false,
        "half": false,
        "tunnel": false,
        "top_color": 0,
        "bottom_color": 4,
        "low3": 4
      },
      null,
      null,
      null
    ],
    [
      null,
      null,
      null,
      {
        "val": 5,
        "full": false,
        "half": false,
        "tunnel": false,
        "top_color": 0,
        "bottom_color": 5,
        "low3": 5
      },
      null,
      null,
      null
    ],
    [
      null,
      null,
      null,
      {
        "val": 6,
        "full": false,
        "half": false,
        "tunnel": false,
        "top_color": 0,
        "bottom_color": 6,
        "low3": 6
      },
      null,
      null,
      null
    ],
    [
      null,
      null,
      null,
      {
        "val": 7,
        "full": false,
        "half": false,
        "tunnel": false,
        "top_color": 0,
        "bottom_color": 7,
        "low3": 7
      },
      null,
      null,
      null
    ],
    [
      null,
      null,
      null,
      {
        "val": 11,
        "full": false,
        "half": false,
        "tunnel": false,
        "top_color": 0,
        "bottom_color": 11,
        "low3": 3
      },
      null,
      null,
      null
    ],
    [
      null,
      null,
      null,
      {
        "val": 13,
        "full": false,
        "half": false,
        "tunnel": false,
        "top_color": 0,
        "bottom_color": 13,
        "low3": 5
      },
      null,
      null,
      null
    ],
    [
      null,
      null,
      null,
      {
        "val": 14,
        "full": false,
        "half": false,
        "tunnel": false,
        "top_color": 0,
        "bottom_color": 14,
        "low3": 6
      },
      null,
      null,
      null
    ],
    [
      null,
      null,
      null,
      {
        "val": 15,
        "full": false,
        "half": false,
        "tunnel": false,
        "top_color": 0,
        "bottom_color": 15,
        "low3": 7
      },
      null,
      null,
      null
    ],
    [
      null,
      null,
      null,
      {
        "val": 799,
        "full": false,
        "half": true,
        "tunnel": true,
        "top_color": 1,
        "bottom_color": 15,
        "low3": 7
      },
      null,
      null,
      null
    ],
    [
      null,
      null,
      null,
      {
        "val": 831,
        "full": false,
        "half": true,
        "tunnel": true,
        "top_color": 3,
        "bottom_color": 15,
        "low3": 7
      },
      null,
      null,
      null
    ],
    [
      null,
      null,
      null,
      {
        "val": 847,
        "full": false,
        "half": true,
        "tunnel": true,
        "top_color": 4,
        "bottom_color": 15,
        "low3": 7
      },
      null,
      null,
      null
    ],
    [
      null,
      null,
      null,
      {
        "val": 863,
        "full": false,
        "half": true,
        "tunnel": true,
        "top_color": 5,
        "bottom_color": 15,
        "low3": 7
      },
      null,
      null,
      null
    ],
    [
      null,
      null,
      null,
      {
        "val": 879,
        "full": false,
        "half": true,
        "tunnel": true,
        "top_color": 6,
        "bottom_color": 15,
        "low3": 7
      },
      null,
      null,
      null
    ],
    [
      null,
      null,
      null,
      {
        "val": 895,
        "full": false,
        "half": true,
        "tunnel": true,
        "top_color": 7,
        "bottom_color": 15,
        "low3": 7
      },
      null,
      null,
      null
    ],
    [
      null,
      null,
      null,
      {
        "val": 959,
        "full": false,
        "half": true,
        "tunnel": true,
        "top_color": 11,
        "bottom_color": 15,
        "low3": 7
      },
      null,
      null,
      null
    ],
    [
      null,
      null,
      null,
      {
        "val": 991,
        "full": false,
        "half": true,
        "tunnel": true,
        "top_color": 13,
        "bottom_color": 15,
        "low3": 7
      },
      null,
      null,
      null
    ],
    [
      null,
      null,
      null,
      {
        "val": 1007,
        "full": false,
        "half": true,
        "tunnel": true,
        "top_color": 14,
        "bottom_color": 15,
        "low3": 7
      },
      null,
      null,
      null
    ],
    [
      null,
      null,
      null,
      {
        "val": 1023,
        "full": false,
        "half": true,
        "tunnel": true,
        "top_color": 15,
        "bottom_color": 15,
        "low3": 7
      },
      null,
      null,
      null
    ],
    [
      null,
      null,
      null,
      {
        "val": 1007,
        "full": false,
        "half": true,
        "tunnel": true,
        "top_color": 14,
        "bottom_color": 15,
        "low3": 7
      },
      null,
      null,
      null
    ],
    [
      null,
      null,
      null,
      {
        "val": 1503,
        "full": true,
        "half": false,
        "tunnel": true,
        "top_color": 13,
        "bottom_color": 15,
        "low3": 7
      },
      null,
      null,
      null
    ],
    [
      null,
      null,
      null,
      {
        "val": 1471,
        "full": true,
        "half": false,
        "tunnel": true,
        "top_color": 11,
        "bottom_color": 15,
        "low3": 7
      },
      null,
      null,
      null
    ],
    [
      null,
      null,
      null,
      {
        "val": 1407,
        "full": true,
        "half": false,
        "tunnel": true,
        "top_color": 7,
        "bottom_color": 15,
        "low3": 7
      },
      null,
      null,
      null
    ],
    [
      null,
      null,
      null,
      {
        "val": 1391,
        "full": true,
        "half": false,
        "tunnel": true,
        "top_color": 6,
        "bottom_color": 15,
        "low3": 7
      },
      null,
      null,
      null
    ],
    [
      null,
      null,
      null,
      {
        "val": 1375,
        "full": true,
        "half": false,
        "tunnel": true,
        "top_color": 5,
        "bottom_color": 15,
        "low3": 7
      },
      null,
      null,
      null
    ],
    [
      null,
      null,
      null,
      {
        "val": 1359,
        "full": true,
        "half": false,
        "tunnel": true,
        "top_color": 4,
        "bottom_color": 15,
        "low3": 7
      },
      null,
      null,
      null
    ],
    [
      null,
      null,
      null,
      {
        "val": 1343,
        "full": true,
        "half": false,
        "tunnel": true,
        "top_color": 3,
        "bottom_color": 15,
        "low3": 7
      },
      null,
      null,
      null
    ],
    [
      null,
      null,
      null,
      {
        "val": 1311,
        "full": true,
        "half": false,
        "tunnel": true,
        "top_color": 1,
        "bottom_color": 15,
        "low3": 7
      },
      null,
      null,
      null
    ],
    [
      null,
      null,
      null,
      {
        "val": 15,
        "full": false,
        "half": false,
        "tunnel": false,
        "top_color": 0,
        "bottom_color": 15,
        "low3": 7
      },
      {
        "val": 15,
        "full": false,
        "half": false,
        "tunnel": false,
        "top_color": 0,
        "bottom_color": 15,
        "low3": 7
      },
      {
        "val": 3,
        "full": false,
        "half": false,
        "tunnel": false,
        "top_color": 0,
        "bottom_color": 3,
        "low3": 3
      },
      null
    ],
    [
      null,
      null,
      null,
      {
        "val": 15,
        "full": false,
        "half": false,
        "tunnel": false,
        "top_color": 0,
        "bottom_color": 15,
        "low3": 7
      },
      {
        "val": 3,
        "full": false,
        "half": false,
        "tunnel": false,
        "top_color": 0,
        "bottom_color": 3,
        "low3": 3
      },
      {
        "val": 4,
        "full": false,
        "half": false,
        "tunnel": false,
        "top_color": 0,
        "bottom_color": 4,
        "low3": 4
      },
      null
    ],
    [
      null,
      null,
      null,
      {
        "val": 15,
        "full": false,
        "half": false,
        "tunnel": false,
        "top_color": 0,
        "bottom_color": 15,
        "low3": 7
      },
      {
        "val": 4,
        "full": false,
        "half": false,
        "tunnel": false,
        "top_color": 0,
        "bottom_color": 4,
        "low3": 4
      },
      {
        "val": 5,
        "full": false,
        "half": false,
        "tunnel": false,
        "top_color": 0,
        "bottom_color": 5,
        "low3": 5
      },
      null
    ],
    [
      null,
      null,
      null,
      {
        "val": 4,
        "full": false,
        "half": false,
        "tunnel": false,
        "top_color": 0,
        "bottom_color": 4,
        "low3": 4
      },
      {
        "val": 5,
        "full": false,
        "half": false,
        "tunnel": false,
        "top_color": 0,
        "bottom_color": 5,
        "low3": 5
      },
      {
        "val": 6,
        "full": false,
        "half": false,
        "tunnel": false,
        "top_color": 0,
        "bottom_color": 6,
        "low3": 6
      },
      null
    ],
    [
      null,
      null,
      null,
      {
        "val": 5,
        "full": false,
        "half": false,
        "tunnel": false,
        "top_color": 0,
        "bottom_color": 5,
        "low3": 5
      },
      {
        "val": 6,
        "full": false,
        "half": false,
        "tunnel": false,
        "top_color": 0,
        "bottom_color": 6,
        "low3": 6
      },
      {
        "val": 7,
        "full": false,
        "half": false,
        "tunnel": false,
        "top_color": 0,
        "bottom_color": 7,
        "low3": 7
      },
      null
    ],
    [
      null,
      null,
      null,
      {
        "val": 6,
        "full": false,
        "half": false,
        "tunnel": false,
        "top_color": 0,
        "bottom_color": 6,
        "low3": 6
      },
      {
        "val": 7,
        "full": false,
        "half": false,
        "tunnel": false,
        "top_color": 0,
        "bottom_color": 7,
        "low3": 7
      },
      {
        "val": 11,
        "full": false,
        "half": false,
        "tunnel": false,
        "top_color": 0,
        "bottom_color": 11,
        "low3": 3
      },
      null
    ],
    [
      null,
      null,
      null,
      {
        "val": 7,
        "full": false,
        "half": false,
        "tunnel": false,
        "top_color": 0,
        "bottom_color": 7,
        "low3": 7
      },
      {
        "val": 11,
        "full": false,
        "half": false,
        "tunnel": false,
        "top_color": 0,
        "bottom_color": 11,
        "low3": 3
      },
      {
        "val": 13,
        "full": false,
        "half": false,
        "tunnel": false,
        "top_color": 0,
        "bottom_color": 13,
        "low3": 5
      },
      null
    ],
    [
      null,
      null,
      null,
      {
        "val": 11,
        "full": false,
        "half": false,
        "tunnel": false,
        "top_color": 0,
        "bottom_color": 11,
        "low3": 3
      },
      {
        "val": 13,
        "full": false,
        "half": false,
        "tunnel": false,
        "top_color": 0,
        "bottom_color": 13,
        "low3": 5
      },
      {
        "val": 14,
        "full": false,
        "half": false,
        "tunnel": false,
        "top_color": 0,
        "bottom_color": 14,
        "low3": 6
      },
      null
    ],
    [
      null,
      null,
      null,
      {
        "val": 14,
        "full": false,
        "half": false,
        "tunnel": false,
        "top_color": 0,
        "bottom_color": 14,
        "low3": 6
      },
      {
        "val": 14,
        "full": false,
        "half": false,
        "tunnel": false,
        "top_color": 0,
        "bottom_color": 14,
        "low3": 6
      },
      {
        "val": 15,
        "full": false,
        "half": false,
        "tunnel": false,
        "top_color": 0,
        "bottom_color": 15,
        "low3": 7
      },
      null
    ],
    [
      null,
      null,
      null,
      {
        "val": 15,
        "full": false,
        "half": false,
        "tunnel": false,
        "top_color": 0,
        "bottom_color": 15,
        "low3": 7
      },
      {
        "val": 14,
        "full": false,
        "half": false,
        "tunnel": false,
        "top_color": 0,
        "bottom_color": 14,
        "low3": 6
      },
      {
        "val": 543,
        "full": false,
        "half": true,
        "tunnel": false,
        "top_color": 1,
        "bottom_color": 15,
        "low3": 7
      },
      null
    ],
    [
      null,
      null,
      null,
      {
        "val": 14,
        "full": false,
        "half": false,
        "tunnel": false,
        "top_color": 0,
        "bottom_color": 14,
        "low3": 6
      },
      null,
      {
        "val": 560,
        "full": false,
        "half": true,
        "tunnel": false,
        "top_color": 3,
        "bottom_color": 0,
        "low3": 0
      },
      null
    ],
    [
      null,
      null,
      null,
      {
        "val": 13,
        "full": false,
        "half": false,
        "tunnel": false,
        "top_color": 0,
        "bottom_color": 13,
        "low3": 5
      },
      null,
      {
        "val": 576,
        "full": false,
        "half": true,
        "tunnel": false,
        "top_color": 4,
        "bottom_color": 0,
        "low3": 0
      },
      null
    ],
    [
      null,
      null,
      null,
      {
        "val": 11,
        "full": false,
        "half": false,
        "tunnel": false,
        "top_color": 0,
        "bottom_color": 11,
        "low3": 3
      },
      null,
      {
        "val": 592,
        "full": false,
        "half": true,
        "tunnel": false,
        "top_color": 5,
        "bottom_color": 0,
        "low3": 0
      },
      null
    ],
    [
      null,
      null,
      null,
      {
        "val": 7,
        "full": false,
        "half": false,
        "tunnel": false,
        "top_color": 0,
        "bottom_color": 7,
        "low3": 7
      },
      null,
      {
        "val": 608,
        "full": false,
        "half": true,
        "tunnel": false,
        "top_color": 6,
        "bottom_color": 0,
        "low3": 0
      },
      null
    ],
    [
      null,
      null,
      null,
      {
        "val": 6,
        "full": false,
        "half": false,
        "tunnel": false,
        "top_color": 0,
        "bottom_color": 6,
        "low3": 6
      },
      null,
      {
        "val": 624,
        "full": false,
        "half": true,
        "tunnel": false,
        "top_color": 7,
        "bottom_color": 0,
        "low3": 0
      },
      null
    ],
    [
      null,
      null,
      null,
      {
        "val": 5,
        "full": false,
        "half": false,
        "tunnel": false,
        "top_color": 0,
        "bottom_color": 5,
        "low3": 5
      },
      null,
      {
        "val": 688,
        "full": false,
        "half": true,
        "tunnel": false,
        "top_color": 11,
        "bottom_color": 0,
        "low3": 0
      },
      null
    ],
    [
      null,
      null,
      null,
      {
        "val": 4,
        "full": false,
        "half": false,
        "tunnel": false,
        "top_color": 0,
        "bottom_color": 4,
        "low3": 4
      },
      null,
      {
        "val": 720,
        "full": false,
        "half": true,
        "tunnel": false,
        "top_color": 13,
        "bottom_color": 0,
        "low3": 0
      },
      null
    ],
    [
      null,
      null,
      null,
      {
        "val": 3,
        "full": false,
        "half": false,
        "tunnel": false,
        "top_color": 0,
        "bottom_color": 3,
        "low3": 3
      },
      null,
      {
        "val": 736,
        "full": false,
        "half": true,
        "tunnel": false,
        "top_color": 14,
        "bottom_color": 0,
        "low3": 0
      },
      null
    ],
    [
      null,
      null,
      null,
      {
        "val": 1,
        "full": false,
        "half": false,
        "tunnel": false,
        "top_color": 0,
        "bottom_color": 1,
        "low3": 1
      },
      null,
      {
        "val": 1248,
        "full": true,
        "half": false,
        "tunnel": false,
        "top_color": 14,
        "bottom_color": 0,
        "low3": 0
      },
      null
    ],
    [
      null,
      null,
      null,
      {
        "val": 12,
        "full": false,
        "half": false,
        "tunnel": false,
        "top_color": 0,
        "bottom_color": 12,
        "low3": 4
      },
      null,
      {
        "val": 1232,
        "full": true,
        "half": false,
        "tunnel": false,
        "top_color": 13,
        "bottom_color": 0,
        "low3": 0
      },
      null
    ],
    [
      null,
      null,
      null,
      {
        "val": 12,
        "full": false,
        "half": false,
        "tunnel": false,
        "top_color": 0,
        "bottom_color": 12,
        "low3": 4
      },
      null,
      {
        "val": 1200,
        "full": true,
        "half": false,
        "tunnel": false,
        "top_color": 11,
        "bottom_color": 0,
        "low3": 0
      },
      null
    ],
    [
      null,
      null,
      null,
      {
        "val": 1,
        "full": false,
        "half": false,
        "tunnel": false,
        "top_color": 0,
        "bottom_color": 1,
        "low3": 1
      },
      null,
      {
        "val": 1136,
        "full": true,
        "half": false,
        "tunnel": false,
        "top_color": 7,
        "bottom_color": 0,
        "low3": 0
      },
      null
    ],
    [
      null,
      null,
      null,
      {
        "val": 3,
        "full": false,
        "half": false,
        "tunnel": false,
        "top_color": 0,
        "bottom_color": 3,
        "low3": 3
      },
      null,
      {
        "val": 1120,
        "full": true,
        "half": false,
        "tunnel": false,
        "top_color": 6,
        "bottom_color": 0,
        "low3": 0
      },
      null
    ],
    [
      null,
      null,
      null,
      {
        "val": 4,
        "full": false,
        "half": false,
        "tunnel": false,
        "top_color": 0,
        "bottom_color": 4,
        "low3": 4
      },
      null,
      {
        "val": 1104,
        "full": true,
        "half": false,
        "tunnel": false,
        "top_color": 5,
        "bottom_color": 0,
        "low3": 0
      },
      null
    ],
    [
      null,
      null,
      null,
      {
        "val": 5,
        "full": false,
        "half": false,
        "tunnel": false,
        "top_color": 0,
        "bottom_color": 5,
        "low3": 5
      },
      null,
      {
        "val": 1088,
        "full": true,
        "half": false,
        "tunnel": false,
        "top_color": 4,
        "bottom_color": 0,
        "low3": 0
      },
      null
    ],
    [
      null,
      null,
      null,
      {
        "val": 6,
        "full": false,
        "half": false,
        "tunnel": false,
        "top_color": 0,
        "bottom_color": 6,
        "low3": 6
      },
      null,
      {
        "val": 1072,
        "full": true,
        "half": false,
        "tunnel": false,
        "top_color": 3,
        "bottom_color": 0,
        "low3": 0
      },
      null
    ],
    [
      null,
      null,
      null,
      {
        "val": 7,
        "full": false,
        "half": false,
        "tunnel": false,
        "top_color": 0,
        "bottom_color": 7,
        "low3": 7
      },
      null,
      null,
      null
    ],
    [
      null,
      null,
      null,
      {
        "val": 11,
        "full": false,
        "half": false,
        "tunnel": false,
        "top_color": 0,
        "bottom_color": 11,
        "low3": 3
      },
      null,
      null,
      null
    ],
    [
      null,
      null,
      null,
      {
        "val": 13,
        "full": false,
        "half": false,
        "tunnel": false,
        "top_color": 0,
        "bottom_color": 13,
        "low3": 5
      },
      null,
      null,
      null
    ],
    [
      null,
      null,
      null,
      {
        "val": 14,
        "full": false,
        "half": false,
        "tunnel": false,
        "top_color": 0,
        "bottom_color": 14,
        "low3": 6
      },
      null,
      null,
      null
    ],
    [
      null,
      null,
      null,
      {
        "val": 15,
        "full": false,
        "half": false,
        "tunnel": false,
        "top_color": 0,
        "bottom_color": 15,
        "low3": 7
      },
      null,
      null,
      null
    ],
    [
      null,
      null,
      null,
      {
        "val": 271,
        "full": false,
        "half": false,
        "tunnel": true,
        "top_color": 0,
        "bottom_color": 15,
        "low3": 7
      },
      null,
      null,
      null
    ],
    [
      null,
      null,
      null,
      {
        "val": 15,
        "full": false,
        "half": false,
        "tunnel": false,
        "top_color": 0,
        "bottom_color": 15,
        "low3": 7
      },
      null,
      null,
      null
    ],
    [
      null,
      null,
      null,
      {
        "val": 271,
        "full": false,
        "half": false,
        "tunnel": true,
        "top_color": 0,
        "bottom_color": 15,
        "low3": 7
      },
      null,
      null,
      null
    ],
    [
      null,
      null,
      null,
      {
        "val": 271,
        "full": false,
        "half": false,
        "tunnel": true,
        "top_color": 0,
        "bottom_color": 15,
        "low3": 7
      },
      null,
      null,
      null
    ],
    [
      null,
      null,
      null,
      {
        "val": 15,
        "full": false,
        "half": false,
        "tunnel": false,
        "top_color": 0,
        "bottom_color": 15,
        "low3": 7
      },
      null,
      null,
      null
    ],
    [
      null,
      null,
      null,
      {
        "val": 15,
        "full": false,
        "half": false,
        "tunnel": false,
        "top_color": 0,
        "bottom_color": 15,
        "low3": 7
      },
      null,
      null,
      null
    ],
    [
      null,
      null,
      null,
      {
        "val": 15,
        "full": false,
        "half": false,
        "tunnel": false,
        "top_color": 0,
        "bottom_color": 15,
        "low3": 7
      },
      null,
      null,
      null
    ],
    [
      null,
      null,
      null,
      {
        "val": 15,
        "full": false,
        "half": false,
        "tunnel": false,
        "top_color": 0,
        "bottom_color": 15,
        "low3": 7
      },
      null,
      null,
      null
    ],
    [
      null,
      null,
      null,
      {
        "val": 271,
        "full": false,
        "half": false,
        "tunnel": true,
        "top_color": 0,
        "bottom_color": 15,
        "low3": 7
      },
      null,
      null,
      null
    ],
    [
      null,
      null,
      null,
      {
        "val": 271,
        "full": false,
        "half": false,
        "tunnel": true,
        "top_color": 0,
        "bottom_color": 15,
        "low3": 7
      },
      {
        "val": 15,
        "full": false,
        "half": false,
        "tunnel": false,
        "top_color": 0,
        "bottom_color": 15,
        "low3": 7
      },
      null,
      null
    ],
    [
      null,
      null,
      null,
      {
        "val": 271,
        "full": false,
        "half": false,
        "tunnel": true,
        "top_color": 0,
        "bottom_color": 15,
        "low3": 7
      },
      {
        "val": 14,
        "full": false,
        "half": false,
        "tunnel": false,
        "top_color": 0,
        "bottom_color": 14,
        "low3": 6
      },
      {
        "val": 15,
        "full": false,
        "half": false,
        "tunnel": false,
        "top_color": 0,
        "bottom_color": 15,
        "low3": 7
      },
      null
    ],
    [
      null,
      null,
      null,
      {
        "val": 271,
        "full": false,
        "half": false,
        "tunnel": true,
        "top_color": 0,
        "bottom_color": 15,
        "low3": 7
      },
      {
        "val": 13,
        "full": false,
        "half": false,
        "tunnel": false,
        "top_color": 0,
        "bottom_color": 13,
        "low3": 5
      },
      {
        "val": 14,
        "full": false,
        "half": false,
        "tunnel": false,
        "top_color": 0,
        "bottom_color": 14,
        "low3": 6
      },
      {
        "val": 15,
        "full": false,
        "half": false,
        "tunnel": false,
        "top_color": 0,
        "bottom_color": 15,
        "low3": 7
      }
    ],
    [
      null,
      null,
      null,
      {
        "val": 268,
        "full": false,
        "half": false,
        "tunnel": true,
        "top_color": 0,
        "bottom_color": 12,
        "low3": 4
      },
      {
        "val": 11,
        "full": false,
        "half": false,
        "tunnel": false,
        "top_color": 0,
        "bottom_color": 11,
        "low3": 3
      },
      {
        "val": 13,
        "full": false,
        "half": false,
        "tunnel": false,
        "top_color": 0,
        "bottom_color": 13,
        "low3": 5
      },
      {
        "val": 14,
        "full": false,
        "half": false,
        "tunnel": false,
        "top_color": 0,
        "bottom_color": 14,
        "low3": 6
      }
    ],
    [
      null,
      null,
      null,
      {
        "val": 268,
        "full": false,
        "half": false,
        "tunnel": true,
        "top_color": 0,
        "bottom_color": 12,
        "low3": 4
      },
      {
        "val": 7,
        "full": false,
        "half": false,
        "tunnel": false,
        "top_color": 0,
        "bottom_color": 7,
        "low3": 7
      },
      {
        "val": 11,
        "full": false,
        "half": false,
        "tunnel": false,
        "top_color": 0,
        "bottom_color": 11,
        "low3": 3
      },
      {
        "val": 13,
        "full": false,
        "half": false,
        "tunnel": false,
        "top_color": 0,
        "bottom_color": 13,
        "low3": 5
      }
    ],
    [
      null,
      null,
      null,
      {
        "val": 268,
        "full": false,
        "half": false,
        "tunnel": true,
        "top_color": 0,
        "bottom_color": 12,
        "low3": 4
      },
      {
        "val": 6,
        "full": false,
        "half": false,
        "tunnel": false,
        "top_color": 0,
        "bottom_color": 6,
        "low3": 6
      },
      {
        "val": 7,
        "full": false,
        "half": false,
        "tunnel": false,
        "top_color": 0,
        "bottom_color": 7,
        "low3": 7
      },
      {
        "val": 11,
        "full": false,
        "half": false,
        "tunnel": false,
        "top_color": 0,
        "bottom_color": 11,
        "low3": 3
      }
    ],
    [
      null,
      null,
      null,
      {
        "val": 268,
        "full": false,
        "half": false,
        "tunnel": true,
        "top_color": 0,
        "bottom_color": 12,
        "low3": 4
      },
      {
        "val": 5,
        "full": false,
        "half": false,
        "tunnel": false,
        "top_color": 0,
        "bottom_color": 5,
        "low3": 5
      },
      {
        "val": 6,
        "full": false,
        "half": false,
        "tunnel": false,
        "top_color": 0,
        "bottom_color": 6,
        "low3": 6
      },
      {
        "val": 7,
        "full": false,
        "half": false,
        "tunnel": false,
        "top_color": 0,
        "bottom_color": 7,
        "low3": 7
      }
    ],
    [
      null,
      null,
      null,
      {
        "val": 268,
        "full": false,
        "half": false,
        "tunnel": true,
        "top_color": 0,
        "bottom_color": 12,
        "low3": 4
      },
      {
        "val": 4,
        "full": false,
        "half": false,
        "tunnel": false,
        "top_color": 0,
        "bottom_color": 4,
        "low3": 4
      },
      {
        "val": 5,
        "full": false,
        "half": false,
        "tunnel": false,
        "top_color": 0,
        "bottom_color": 5,
        "low3": 5
      },
      {
        "val": 6,
        "full": false,
        "half": false,
        "tunnel": false,
        "top_color": 0,
        "bottom_color": 6,
        "low3": 6
      }
    ],
    [
      null,
      null,
      null,
      {
        "val": 268,
        "full": false,
        "half": false,
        "tunnel": true,
        "top_color": 0,
        "bottom_color": 12,
        "low3": 4
      },
      {
        "val": 3,
        "full": false,
        "half": false,
        "tunnel": false,
        "top_color": 0,
        "bottom_color": 3,
        "low3": 3
      },
      {
        "val": 4,
        "full": false,
        "half": false,
        "tunnel": false,
        "top_color": 0,
        "bottom_color": 4,
        "low3": 4
      },
      {
        "val": 5,
        "full": false,
        "half": false,
        "tunnel": false,
        "top_color": 0,
        "bottom_color": 5,
        "low3": 5
      }
    ],
    [
      null,
      null,
      null,
      {
        "val": 268,
        "full": false,
        "half": false,
        "tunnel": true,
        "top_color": 0,
        "bottom_color": 12,
        "low3": 4
      },
      null,
      {
        "val": 3,
        "full": false,
        "half": false,
        "tunnel": false,
        "top_color": 0,
        "bottom_color": 3,
        "low3": 3
      },
      {
        "val": 4,
        "full": false,
        "half": false,
        "tunnel": false,
        "top_color": 0,
        "bottom_color": 4,
        "low3": 4
      }
    ],
    [
      null,
      null,
      null,
      {
        "val": 15,
        "full": false,
        "half": false,
        "tunnel": false,
        "top_color": 0,
        "bottom_color": 15,
        "low3": 7
      },
      null,
      null,
      {
        "val": 3,
        "full": false,
        "half": false,
        "tunnel": false,
        "top_color": 0,
        "bottom_color": 3,
        "low3": 3
      }
    ],
    [
      null,
      null,
      null,
      {
        "val": 15,
        "full": false,
        "half": false,
        "tunnel": false,
        "top_color": 0,
        "bottom_color": 15,
        "low3": 7
      },
      null,
      null,
      {
        "val": 1,
        "full": false,
        "half": false,
        "tunnel": false,
        "top_color": 0,
        "bottom_color": 1,
        "low3": 1
      }
    ],
    [
      null,
      null,
      null,
      {
        "val": 15,
        "full": false,
        "half": false,
        "tunnel": false,
        "top_color": 0,
        "bottom_color": 15,
        "low3": 7
      },
      null,
      null,
      {
        "val": 3,
        "full": false,
        "half": false,
        "tunnel": false,
        "top_color": 0,
        "bottom_color": 3,
        "low3": 3
      }
    ],
    [
      null,
      null,
      null,
      {
        "val": 15,
        "full": false,
        "half": false,
        "tunnel": false,
        "top_color": 0,
        "bottom_color": 15,
        "low3": 7
      },
      null,
      null,
      {
        "val": 4,
        "full": false,
        "half": false,
        "tunnel": false,
        "top_color": 0,
        "bottom_color": 4,
        "low3": 4
      }
    ],
    [
      null,
      null,
      null,
      {
        "val": 15,
        "full": false,
        "half": false,
        "tunnel": false,
        "top_color": 0,
        "bottom_color": 15,
        "low3": 7
      },
      null,
      null,
      {
        "val": 5,
        "full": false,
        "half": false,
        "tunnel": false,
        "top_color": 0,
        "bottom_color": 5,
        "low3": 5
      }
    ],
    [
      null,
      null,
      null,
      {
        "val": 15,
        "full": false,
        "half": false,
        "tunnel": false,
        "top_color": 0,
        "bottom_color": 15,
        "low3": 7
      },
      null,
      null,
      {
        "val": 6,
        "full": false,
        "half": false,
        "tunnel": false,
        "top_color": 0,
        "bottom_color": 6,
        "low3": 6
      }
    ],
    [
      null,
      null,
      null,
      {
        "val": 15,
        "full": false,
        "half": false,
        "tunnel": false,
        "top_color": 0,
        "bottom_color": 15,
        "low3": 7
      },
      null,
      null,
      {
        "val": 7,
        "full": false,
        "half": false,
        "tunnel": false,
        "top_color": 0,
        "bottom_color": 7,
        "low3": 7
      }
    ],
    [
      null,
      null,
      null,
      null,
      null,
      null,
      {
        "val": 11,
        "full": false,
        "half": false,
        "tunnel": false,
        "top_color": 0,
        "bottom_color": 11,
        "low3": 3
      }
    ],
    [
      null,
      null,
      null,
      null,
      null,
      null,
      {
        "val": 13,
        "full": false,
        "half": false,
        "tunnel": false,
        "top_color": 0,
        "bottom_color": 13,
        "low3": 5
      }
    ],
    [
      null,
      null,
      null,
      null,
      null,
      null,
      {
        "val": 14,
        "full": false,
        "half": false,
        "tunnel": false,
        "top_color": 0,
        "bottom_color": 14,
        "low3": 6
      }
    ],
    [
      null,
      null,
      null,
      null,
      null,
      null,
      {
        "val": 15,
        "full": false,
        "half": false,
        "tunnel": false,
        "top_color": 0,
        "bottom_color": 15,
        "low3": 7
      }
    ],
    [
      null,
      null,
      null,
      null,
      null,
      {
        "val": 15,
        "full": false,
        "half": false,
        "tunnel": false,
        "top_color": 0,
        "bottom_color": 15,
        "low3": 7
      },
      {
        "val": 14,
        "full": false,
        "half": false,
        "tunnel": false,
        "top_color": 0,
        "bottom_color": 14,
        "low3": 6
      }
    ],
    [
      null,
      null,
      null,
      null,
      {
        "val": 15,
        "full": false,
        "half": false,
        "tunnel": false,
        "top_color": 0,
        "bottom_color": 15,
        "low3": 7
      },
      {
        "val": 14,
        "full": false,
        "half": false,
        "tunnel": false,
        "top_color": 0,
        "bottom_color": 14,
        "low3": 6
      },
      {
        "val": 13,
        "full": false,
        "half": false,
        "tunnel": false,
        "top_color": 0,
        "bottom_color": 13,
        "low3": 5
      }
    ],
    [
      null,
      null,
      null,
      {
        "val": 15,
        "full": false,
        "half": false,
        "tunnel": false,
        "top_color": 0,
        "bottom_color": 15,
        "low3": 7
      },
      {
        "val": 14,
        "full": false,
        "half": false,
        "tunnel": false,
        "top_color": 0,
        "bottom_color": 14,
        "low3": 6
      },
      {
        "val": 13,
        "full": false,
        "half": false,
        "tunnel": false,
        "top_color": 0,
        "bottom_color": 13,
        "low3": 5
      },
      {
        "val": 11,
        "full": false,
        "half": false,
        "tunnel": false,
        "top_color": 0,
        "bottom_color": 11,
        "low3": 3
      }
    ],
    [
      null,
      null,
      {
        "val": 15,
        "full": false,
        "half": false,
        "tunnel": false,
        "top_color": 0,
        "bottom_color": 15,
        "low3": 7
      },
      {
        "val": 14,
        "full": false,
        "half": false,
        "tunnel": false,
        "top_color": 0,
        "bottom_color": 14,
        "low3": 6
      },
      {
        "val": 13,
        "full": false,
        "half": false,
        "tunnel": false,
        "top_color": 0,
        "bottom_color": 13,
        "low3": 5
      },
      {
        "val": 11,
        "full": false,
        "half": false,
        "tunnel": false,
        "top_color": 0,
        "bottom_color": 11,
        "low3": 3
      },
      {
        "val": 7,
        "full": false,
        "half": false,
        "tunnel": false,
        "top_color": 0,
        "bottom_color": 7,
        "low3": 7
      }
    ],
    [
      null,
      {
        "val": 15,
        "full": false,
        "half": false,
        "tunnel": false,
        "top_color": 0,
        "bottom_color": 15,
        "low3": 7
      },
      {
        "val": 14,
        "full": false,
        "half": false,
        "tunnel": false,
        "top_color": 0,
        "bottom_color": 14,
        "low3": 6
      },
      {
        "val": 13,
        "full": false,
        "half": false,
        "tunnel": false,
        "top_color": 0,
        "bottom_color": 13,
        "low3": 5
      },
      {
        "val": 11,
        "full": false,
        "half": false,
        "tunnel": false,
        "top_color": 0,
        "bottom_color": 11,
        "low3": 3
      },
      {
        "val": 7,
        "full": false,
        "half": false,
        "tunnel": false,
        "top_color": 0,
        "bottom_color": 7,
        "low3": 7
      },
      {
        "val": 6,
        "full": false,
        "half": false,
        "tunnel": false,
        "top_color": 0,
        "bottom_color": 6,
        "low3": 6
      }
    ],
    [
      {
        "val": 15,
        "full": false,
        "half": false,
        "tunnel": false,
        "top_color": 0,
        "bottom_color": 15,
        "low3": 7
      },
      {
        "val": 14,
        "full": false,
        "half": false,
        "tunnel": false,
        "top_color": 0,
        "bottom_color": 14,
        "low3": 6
      },
      {
        "val": 13,
        "full": false,
        "half": false,
        "tunnel": false,
        "top_color": 0,
        "bottom_color": 13,
        "low3": 5
      },
      {
        "val": 11,
        "full": false,
        "half": false,
        "tunnel": false,
        "top_color": 0,
        "bottom_color": 11,
        "low3": 3
      },
      {
        "val": 7,
        "full": false,
        "half": false,
        "tunnel": false,
        "top_color": 0,
        "bottom_color": 7,
        "low3": 7
      },
      {
        "val": 6,
        "full": false,
        "half": false,
        "tunnel": false,
        "top_color": 0,
        "bottom_color": 6,
        "low3": 6
      },
      {
        "val": 5,
        "full": false,
        "half": false,
        "tunnel": false,
        "top_color": 0,
        "bottom_color": 5,
        "low3": 5
      }
    ],
    [
      {
        "val": 14,
        "full": false,
        "half": false,
        "tunnel": false,
        "top_color": 0,
        "bottom_color": 14,
        "low3": 6
      },
      {
        "val": 13,
        "full": false,
        "half": false,
        "tunnel": false,
        "top_color": 0,
        "bottom_color": 13,
        "low3": 5
      },
      {
        "val": 11,
        "full": false,
        "half": false,
        "tunnel": false,
        "top_color": 0,
        "bottom_color": 11,
        "low3": 3
      },
      {
        "val": 7,
        "full": false,
        "half": false,
        "tunnel": false,
        "top_color": 0,
        "bottom_color": 7,
        "low3": 7
      },
      {
        "val": 6,
        "full": false,
        "half": false,
        "tunnel": false,
        "top_color": 0,
        "bottom_color": 6,
        "low3": 6
      },
      {
        "val": 5,
        "full": false,
        "half": false,
        "tunnel": false,
        "top_color": 0,
        "bottom_color": 5,
        "low3": 5
      },
      {
        "val": 4,
        "full": false,
        "half": false,
        "tunnel": false,
        "top_color": 0,
        "bottom_color": 4,
        "low3": 4
      }
    ],
    [
      {
        "val": 13,
        "full": false,
        "half": false,
        "tunnel": false,
        "top_color": 0,
        "bottom_color": 13,
        "low3": 5
      },
      {
        "val": 11,
        "full": false,
        "half": false,
        "tunnel": false,
        "top_color": 0,
        "bottom_color": 11,
        "low3": 3
      },
      {
        "val": 7,
        "full": false,
        "half": false,
        "tunnel": false,
        "top_color": 0,
        "bottom_color": 7,
        "low3": 7
      },
      {
        "val": 6,
        "full": false,
        "half": false,
        "tunnel": false,
        "top_color": 0,
        "bottom_color": 6,
        "low3": 6
      },
      {
        "val": 5,
        "full": false,
        "half": false,
        "tunnel": false,
        "top_color": 0,
        "bottom_color": 5,
        "low3": 5
      },
      {
        "val": 4,
        "full": false,
        "half": false,
        "tunnel": false,
        "top_color": 0,
        "bottom_color": 4,
        "low3": 4
      },
      {
        "val": 3,
        "full": false,
        "half": false,
        "tunnel": false,
        "top_color": 0,
        "bottom_color": 3,
        "low3": 3
      }
    ],
    [
      {
        "val": 11,
        "full": false,
        "half": false,
        "tunnel": false,
        "top_color": 0,
        "bottom_color": 11,
        "low3": 3
      },
      {
        "val": 7,
        "full": false,
        "half": false,
        "tunnel": false,
        "top_color": 0,
        "bottom_color": 7,
        "low3": 7
      },
      {
        "val": 6,
        "full": false,
        "half": false,
        "tunnel": false,
        "top_color": 0,
        "bottom_color": 6,
        "low3": 6
      },
      {
        "val": 5,
        "full": false,
        "half": false,
        "tunnel": false,
        "top_color": 0,
        "bottom_color": 5,
        "low3": 5
      },
      {
        "val": 4,
        "full": false,
        "half": false,
        "tunnel": false,
        "top_color": 0,
        "bottom_color": 4,
        "low3": 4
      },
      {
        "val": 3,
        "full": false,
        "half": false,
        "tunnel": false,
        "top_color": 0,
        "bottom_color": 3,
        "low3": 3
      },
      {
        "val": 1,
        "full": false,
        "half": false,
        "tunnel": false,
        "top_color": 0,
        "bottom_color": 1,
        "low3": 1
      }
    ],
    [
      {
        "val": 7,
        "full": false,
        "half": false,
        "tunnel": false,
        "top_color": 0,
        "bottom_color": 7,
        "low3": 7
      },
      {
        "val": 6,
        "full": false,
        "half": false,
        "tunnel": false,
        "top_color": 0,
        "bottom_color": 6,
        "low3": 6
      },
      {
        "val": 5,
        "full": false,
        "half": false,
        "tunnel": false,
        "top_color": 0,
        "bottom_color": 5,
        "low3": 5
      },
      {
        "val": 4,
        "full": false,
        "half": false,
        "tunnel": false,
        "top_color": 0,
        "bottom_color": 4,
        "low3": 4
      },
      {
        "val": 3,
        "full": false,
        "half": false,
        "tunnel": false,
        "top_color": 0,
        "bottom_color": 3,
        "low3": 3
      },
      {
        "val": 1,
        "full": false,
        "half": false,
        "tunnel": false,
        "top_color": 0,
        "bottom_color": 1,
        "low3": 1
      },
      null
    ],
    [
      {
        "val": 6,
        "full": false,
        "half": false,
        "tunnel": false,
        "top_color": 0,
        "bottom_color": 6,
        "low3": 6
      },
      {
        "val": 5,
        "full": false,
        "half": false,
        "tunnel": false,
        "top_color": 0,
        "bottom_color": 5,
        "low3": 5
      },
      {
        "val": 4,
        "full": false,
        "half": false,
        "tunnel": false,
        "top_color": 0,
        "bottom_color": 4,
        "low3": 4
      },
      {
        "val": 3,
        "full": false,
        "half": false,
        "tunnel": false,
        "top_color": 0,
        "bottom_color": 3,
        "low3": 3
      },
      {
        "val": 1,
        "full": false,
        "half": false,
        "tunnel": false,
        "top_color": 0,
        "bottom_color": 1,
        "low3": 1
      },
      null,
      {
        "val": 1,
        "full": false,
        "half": false,
        "tunnel": false,
        "top_color": 0,
        "bottom_color": 1,
        "low3": 1
      }
    ],
    [
      {
        "val": 5,
        "full": false,
        "half": false,
        "tunnel": false,
        "top_color": 0,
        "bottom_color": 5,
        "low3": 5
      },
      {
        "val": 4,
        "full": false,
        "half": false,
        "tunnel": false,
        "top_color": 0,
        "bottom_color": 4,
        "low3": 4
      },
      {
        "val": 3,
        "full": false,
        "half": false,
        "tunnel": false,
        "top_color": 0,
        "bottom_color": 3,
        "low3": 3
      },
      {
        "val": 1,
        "full": false,
        "half": false,
        "tunnel": false,
        "top_color": 0,
        "bottom_color": 1,
        "low3": 1
      },
      null,
      {
        "val": 1,
        "full": false,
        "half": false,
        "tunnel": false,
        "top_color": 0,
        "bottom_color": 1,
        "low3": 1
      },
      null
    ],
    [
      {
        "val": 4,
        "full": false,
        "half": false,
        "tunnel": false,
        "top_color": 0,
        "bottom_color": 4,
        "low3": 4
      },
      {
        "val": 3,
        "full": false,
        "half": false,
        "tunnel": false,
        "top_color": 0,
        "bottom_color": 3,
        "low3": 3
      },
      {
        "val": 1,
        "full": false,
        "half": false,
        "tunnel": false,
        "top_color": 0,
        "bottom_color": 1,
        "low3": 1
      },
      null,
      {
        "val": 1,
        "full": false,
        "half": false,
        "tunnel": false,
        "top_color": 0,
        "bottom_color": 1,
        "low3": 1
      },
      null,
      {
        "val": 1,
        "full": false,
        "half": false,
        "tunnel": false,
        "top_color": 0,
        "bottom_color": 1,
        "low3": 1
      }
    ],
    [
      {
        "val": 3,
        "full": false,
        "half": false,
        "tunnel": false,
        "top_color": 0,
        "bottom_color": 3,
        "low3": 3
      },
      {
        "val": 1,
        "full": false,
        "half": false,
        "tunnel": false,
        "top_color": 0,
        "bottom_color": 1,
        "low3": 1
      },
      null,
      {
        "val": 1,
        "full": false,
        "half": false,
        "tunnel": false,
        "top_color": 0,
        "bottom_color": 1,
        "low3": 1
      },
      null,
      {
        "val": 1,
        "full": false,
        "half": false,
        "tunnel": false,
        "top_color": 0,
        "bottom_color": 1,
        "low3": 1
      },
      null
    ],
    [
      {
        "val": 1,
        "full": false,
        "half": false,
        "tunnel": false,
        "top_color": 0,
        "bottom_color": 1,
        "low3": 1
      },
      {
        "val": 1,
        "full": false,
        "half": false,
        "tunnel": false,
        "top_color": 0,
        "bottom_color": 1,
        "low3": 1
      },
      {
        "val": 1,
        "full": false,
        "half": false,
        "tunnel": false,
        "top_color": 0,
        "bottom_color": 1,
        "low3": 1
      },
      null,
      {
        "val": 1,
        "full": false,
        "half": false,
        "tunnel": false,
        "top_color": 0,
        "bottom_color": 1,
        "low3": 1
      },
      null,
      {
        "val": 1,
        "full": false,
        "half": false,
        "tunnel": false,
        "top_color": 0,
        "bottom_color": 1,
        "low3": 1
      }
    ],
    [
      null,
      {
        "val": 1,
        "full": false,
        "half": false,
        "tunnel": false,
        "top_color": 0,
        "bottom_color": 1,
        "low3": 1
      },
      {
        "val": 1,
        "full": false,
        "half": false,
        "tunnel": false,
        "top_color": 0,
        "bottom_color": 1,
        "low3": 1
      },
      {
        "val": 1,
        "full": false,
        "half": false,
        "tunnel": false,
        "top_color": 0,
        "bottom_color": 1,
        "low3": 1
      },
      null,
      {
        "val": 1,
        "full": false,
        "half": false,
        "tunnel": false,
        "top_color": 0,
        "bottom_color": 1,
        "low3": 1
      },
      null
    ],
    [
      null,
      null,
      {
        "val": 1,
        "full": false,
        "half": false,
        "tunnel": false,
        "top_color": 0,
        "bottom_color": 1,
        "low3": 1
      },
      {
        "val": 1,
        "full": false,
        "half": false,
        "tunnel": false,
        "top_color": 0,
        "bottom_color": 1,
        "low3": 1
      },
      {
        "val": 1,
        "full": false,
        "half": false,
        "tunnel": false,
        "top_color": 0,
        "bottom_color": 1,
        "low3": 1
      },
      null,
      {
        "val": 1,
        "full": false,
        "half": false,
        "tunnel": false,
        "top_color": 0,
        "bottom_color": 1,
        "low3": 1
      }
    ],
    [
      null,
      null,
      null,
      {
        "val": 1,
        "full": false,
        "half": false,
        "tunnel": false,
        "top_color": 0,
        "bottom_color": 1,
        "low3": 1
      },
      {
        "val": 1,
        "full": false,
        "half": false,
        "tunnel": false,
        "top_color": 0,
        "bottom_color": 1,
        "low3": 1
      },
      {
        "val": 1,
        "full": false,
        "half": false,
        "tunnel": false,
        "top_color": 0,
        "bottom_color": 1,
        "low3": 1
      },
      null
    ],
    [
      null,
      null,
      null,
      null,
      {
        "val": 1,
        "full": false,
        "half": false,
        "tunnel": false,
        "top_color": 0,
        "bottom_color": 1,
        "low3": 1
      },
      {
        "val": 1,
        "full": false,
        "half": false,
        "tunnel": false,
        "top_color": 0,
        "bottom_color": 1,
        "low3": 1
      },
      {
        "val": 1,
        "full": false,
        "half": false,
        "tunnel": false,
        "top_color": 0,
        "bottom_color": 1,
        "low3": 1
      }
    ],
    [
      null,
      null,
      null,
      null,
      null,
      {
        "val": 1,
        "full": false,
        "half": false,
        "tunnel": false,
        "top_color": 0,
        "bottom_color": 1,
        "low3": 1
      },
      {
        "val": 1,
        "full": false,
        "half": false,
        "tunnel": false,
        "top_color": 0,
        "bottom_color": 1,
        "low3": 1
      }
    ],
    [
      null,
      null,
      null,
      null,
      null,
      null,
      {
        "val": 1,
        "full": false,
        "half": false,
        "tunnel": false,
        "top_color": 0,
        "bottom_color": 1,
        "low3": 1
      }
    ],
    [
      null,
      null,
      null,
      null,
      null,
      null,
      {
        "val": 1,
        "full": false,
        "half": false,
        "tunnel": false,
        "top_color": 0,
        "bottom_color": 1,
        "low3": 1
      }
    ],
    [
      null,
      null,
      null,
      null,
      null,
      null,
      {
        "val": 1,
        "full": false,
        "half": false,
        "tunnel": false,
        "top_color": 0,
        "bottom_color": 1,
        "low3": 1
      }
    ],
    [
      null,
      null,
      null,
      null,
      null,
      null,
      {
        "val": 1,
        "full": false,
        "half": false,
        "tunnel": false,
        "top_color": 0,
        "bottom_color": 1,
        "low3": 1
      }
    ],
    [
      null,
      null,
      null,
      null,
      null,
      null,
      {
        "val": 1,
        "full": false,
        "half": false,
        "tunnel": false,
        "top_color": 0,
        "bottom_color": 1,
        "low3": 1
      }
    ],
    [
      null,
      null,
      null,
      null,
      null,
      null,
      {
        "val": 1,
        "full": false,
        "half": false,
        "tunnel": false,
        "top_color": 0,
        "bottom_color": 1,
        "low3": 1
      }
    ],
    [
      null,
      null,
      null,
      null,
      null,
      null,
      {
        "val": 1,
        "full": false,
        "half": false,
        "tunnel": false,
        "top_color": 0,
        "bottom_color": 1,
        "low3": 1
      }
    ],
    [
      null,
      null,
      null,
      null,
      null,
      {
        "val": 8,
        "full": false,
        "half": false,
        "tunnel": false,
        "top_color": 0,
        "bottom_color": 8,
        "low3": 0
      },
      {
        "val": 1,
        "full": false,
        "half": false,
        "tunnel": false,
        "top_color": 0,
        "bottom_color": 1,
        "low3": 1
      }
    ],
    [
      null,
      null,
      null,
      null,
      {
        "val": 8,
        "full": false,
        "half": false,
        "tunnel": false,
        "top_color": 0,
        "bottom_color": 8,
        "low3": 0
      },
      {
        "val": 8,
        "full": false,
        "half": false,
        "tunnel": false,
        "top_color": 0,
        "bottom_color": 8,
        "low3": 0
      },
      {
        "val": 1,
        "full": false,
        "half": false,
        "tunnel": false,
        "top_color": 0,
        "bottom_color": 1,
        "low3": 1
      }
    ],
    [
      null,
      null,
      null,
      {
        "val": 8,
        "full": false,
        "half": false,
        "tunnel": false,
        "top_color": 0,
        "bottom_color": 8,
        "low3": 0
      },
      {
        "val": 8,
        "full": false,
        "half": false,
        "tunnel": false,
        "top_color": 0,
        "bottom_color": 8,
        "low3": 0
      },
      {
        "val": 8,
        "full": false,
        "half": false,
        "tunnel": false,
        "top_color": 0,
        "bottom_color": 8,
        "low3": 0
      },
      {
        "val": 1,
        "full": false,
        "half": false,
        "tunnel": false,
        "top_color": 0,
        "bottom_color": 1,
        "low3": 1
      }
    ],
    [
      null,
      null,
      {
        "val": 8,
        "full": false,
        "half": false,
        "tunnel": false,
        "top_color": 0,
        "bottom_color": 8,
        "low3": 0
      },
      {
        "val": 8,
        "full": false,
        "half": false,
        "tunnel": false,
        "top_color": 0,
        "bottom_color": 8,
        "low3": 0
      },
      {
        "val": 8,
        "full": false,
        "half": false,
        "tunnel": false,
        "top_color": 0,
        "bottom_color": 8,
        "low3": 0
      },
      {
        "val": 8,
        "full": false,
        "half": false,
        "tunnel": false,
        "top_color": 0,
        "bottom_color": 8,
        "low3": 0
      },
      {
        "val": 1,
        "full": false,
        "half": false,
        "tunnel": false,
        "top_color": 0,
        "bottom_color": 1,
        "low3": 1
      }
    ],
    [
      null,
      {
        "val": 520,
        "full": false,
        "half": true,
        "tunnel": false,
        "top_color": 0,
        "bottom_color": 8,
        "low3": 0
      },
      {
        "val": 8,
        "full": false,
        "half": false,
        "tunnel": false,
        "top_color": 0,
        "bottom_color": 8,
        "low3": 0
      },
      {
        "val": 8,
        "full": false,
        "half": false,
        "tunnel": false,
        "top_color": 0,
        "bottom_color": 8,
        "low3": 0
      },
      {
        "val": 8,
        "full": false,
        "half": false,
        "tunnel": false,
        "top_color": 0,
        "bottom_color": 8,
        "low3": 0
      },
      {
        "val": 8,
        "full": false,
        "half": false,
        "tunnel": false,
        "top_color": 0,
        "bottom_color": 8,
        "low3": 0
      },
      {
        "val": 1,
        "full": false,
        "half": false,
        "tunnel": false,
        "top_color": 0,
        "bottom_color": 1,
        "low3": 1
      }
    ],
    [
      null,
      {
        "val": 520,
        "full": false,
        "half": true,
        "tunnel": false,
        "top_color": 0,
        "bottom_color": 8,
        "low3": 0
      },
      {
        "val": 8,
        "full": false,
        "half": false,
        "tunnel": false,
        "top_color": 0,
        "bottom_color": 8,
        "low3": 0
      },
      {
        "val": 8,
        "full": false,
        "half": false,
        "tunnel": false,
        "top_color": 0,
        "bottom_color": 8,
        "low3": 0
      },
      {
        "val": 8,
        "full": false,
        "half": false,
        "tunnel": false,
        "top_color": 0,
        "bottom_color": 8,
        "low3": 0
      },
      {
        "val": 8,
        "full": false,
        "half": false,
        "tunnel": false,
        "top_color": 0,
        "bottom_color": 8,
        "low3": 0
      },
      {
        "val": 1,
        "full": false,
        "half": false,
        "tunnel": false,
        "top_color": 0,
        "bottom_color": 1,
        "low3": 1
      }
    ],
    [
      null,
      {
        "val": 520,
        "full": false,
        "half": true,
        "tunnel": false,
        "top_color": 0,
        "bottom_color": 8,
        "low3": 0
      },
      {
        "val": 8,
        "full": false,
        "half": false,
        "tunnel": false,
        "top_color": 0,
        "bottom_color": 8,
        "low3": 0
      },
      {
        "val": 8,
        "full": false,
        "half": false,
        "tunnel": false,
        "top_color": 0,
        "bottom_color": 8,
        "low3": 0
      },
      {
        "val": 8,
        "full": false,
        "half": false,
        "tunnel": false,
        "top_color": 0,
        "bottom_color": 8,
        "low3": 0
      },
      {
        "val": 8,
        "full": false,
        "half": false,
        "tunnel": false,
        "top_color": 0,
        "bottom_color": 8,
        "low3": 0
      },
      {
        "val": 8,
        "full": false,
        "half": false,
        "tunnel": false,
        "top_color": 0,
        "bottom_color": 8,
        "low3": 0
      }
    ],
    [
      null,
      {
        "val": 520,
        "full": false,
        "half": true,
        "tunnel": false,
        "top_color": 0,
        "bottom_color": 8,
        "low3": 0
      },
      {
        "val": 8,
        "full": false,
        "half": false,
        "tunnel": false,
        "top_color": 0,
        "bottom_color": 8,
        "low3": 0
      },
      {
        "val": 520,
        "full": false,
        "half": true,
        "tunnel": false,
        "top_color": 0,
        "bottom_color": 8,
        "low3": 0
      },
      {
        "val": 8,
        "full": false,
        "half": false,
        "tunnel": false,
        "top_color": 0,
        "bottom_color": 8,
        "low3": 0
      },
      {
        "val": 8,
        "full": false,
        "half": false,
        "tunnel": false,
        "top_color": 0,
        "bottom_color": 8,
        "low3": 0
      },
      {
        "val": 8,
        "full": false,
        "half": false,
        "tunnel": false,
        "top_color": 0,
        "bottom_color": 8,
        "low3": 0
      }
    ],
    [
      null,
      {
        "val": 520,
        "full": false,
        "half": true,
        "tunnel": false,
        "top_color": 0,
        "bottom_color": 8,
        "low3": 0
      },
      {
        "val": 8,
        "full": false,
        "half": false,
        "tunnel": false,
        "top_color": 0,
        "bottom_color": 8,
        "low3": 0
      },
      {
        "val": 520,
        "full": false,
        "half": true,
        "tunnel": false,
        "top_color": 0,
        "bottom_color": 8,
        "low3": 0
      },
      {
        "val": 8,
        "full": false,
        "half": false,
        "tunnel": false,
        "top_color": 0,
        "bottom_color": 8,
        "low3": 0
      },
      {
        "val": 8,
        "full": false,
        "half": false,
        "tunnel": false,
        "top_color": 0,
        "bottom_color": 8,
        "low3": 0
      },
      {
        "val": 8,
        "full": false,
        "half": false,
        "tunnel": false,
        "top_color": 0,
        "bottom_color": 8,
        "low3": 0
      }
    ],
    [
      null,
      null,
      {
        "val": 1,
        "full": false,
        "half": false,
        "tunnel": false,
        "top_color": 0,
        "bottom_color": 1,
        "low3": 1
      },
      null,
      {
        "val": 1,
        "full": false,
        "half": false,
        "tunnel": false,
        "top_color": 0,
        "bottom_color": 1,
        "low3": 1
      },
      null,
      null
    ],
    [
      null,
      null,
      {
        "val": 1,
        "full": false,
        "half": false,
        "tunnel": false,
        "top_color": 0,
        "bottom_color": 1,
        "low3": 1
      },
      null,
      {
        "val": 1,
        "full": false,
        "half": false,
        "tunnel": false,
        "top_color": 0,
        "bottom_color": 1,
        "low3": 1
      },
      null,
      null
    ],
    [
      null,
      null,
      {
        "val": 1,
        "full": false,
        "half": false,
        "tunnel": false,
        "top_color": 0,
        "bottom_color": 1,
        "low3": 1
      },
      null,
      {
        "val": 1,
        "full": false,
        "half": false,
        "tunnel": false,
        "top_color": 0,
        "bottom_color": 1,
        "low3": 1
      },
      null,
      null
    ],
    [
      null,
      null,
      {
        "val": 1,
        "full": false,
        "half": false,
        "tunnel": false,
        "top_color": 0,
        "bottom_color": 1,
        "low3": 1
      },
      null,
      {
        "val": 1,
        "full": false,
        "half": false,
        "tunnel": false,
        "top_color": 0,
        "bottom_color": 1,
        "low3": 1
      },
      null,
      null
    ],
    [
      null,
      null,
      {
        "val": 1,
        "full": false,
        "half": false,
        "tunnel": false,
        "top_color": 0,
        "bottom_color": 1,
        "low3": 1
      },
      null,
      {
        "val": 1,
        "full": false,
        "half": false,
        "tunnel": false,
        "top_color": 0,
        "bottom_color": 1,
        "low3": 1
      },
      null,
      null
    ],
    [
      null,
      null,
      {
        "val": 3,
        "full": false,
        "half": false,
        "tunnel": false,
        "top_color": 0,
        "bottom_color": 3,
        "low3": 3
      },
      {
        "val": 1,
        "full": false,
        "half": false,
        "tunnel": false,
        "top_color": 0,
        "bottom_color": 1,
        "low3": 1
      },
      {
        "val": 3,
        "full": false,
        "half": false,
        "tunnel": false,
        "top_color": 0,
        "bottom_color": 3,
        "low3": 3
      },
      null,
      null
    ],
    [
      null,
      null,
      {
        "val": 4,
        "full": false,
        "half": false,
        "tunnel": false,
        "top_color": 0,
        "bottom_color": 4,
        "low3": 4
      },
      {
        "val": 3,
        "full": false,
        "half": false,
        "tunnel": false,
        "top_color": 0,
        "bottom_color": 3,
        "low3": 3
      },
      {
        "val": 4,
        "full": false,
        "half": false,
        "tunnel": false,
        "top_color": 0,
        "bottom_color": 4,
        "low3": 4
      },
      null,
      null
    ],
    [
      null,
      null,
      {
        "val": 5,
        "full": false,
        "half": false,
        "tunnel": false,
        "top_color": 0,
        "bottom_color": 5,
        "low3": 5
      },
      {
        "val": 4,
        "full": false,
        "half": false,
        "tunnel": false,
        "top_color": 0,
        "bottom_color": 4,
        "low3": 4
      },
      {
        "val": 5,
        "full": false,
        "half": false,
        "tunnel": false,
        "top_color": 0,
        "bottom_color": 5,
        "low3": 5
      },
      null,
      null
    ],
    [
      null,
      null,
      {
        "val": 6,
        "full": false,
        "half": false,
        "tunnel": false,
        "top_color": 0,
        "bottom_color": 6,
        "low3": 6
      },
      {
        "val": 5,
        "full": false,
        "half": false,
        "tunnel": false,
        "top_color": 0,
        "bottom_color": 5,
        "low3": 5
      },
      {
        "val": 6,
        "full": false,
        "half": false,
        "tunnel": false,
        "top_color": 0,
        "bottom_color": 6,
        "low3": 6
      },
      null,
      null
    ],
    [
      null,
      null,
      {
        "val": 7,
        "full": false,
        "half": false,
        "tunnel": false,
        "top_color": 0,
        "bottom_color": 7,
        "low3": 7
      },
      {
        "val": 6,
        "full": false,
        "half": false,
        "tunnel": false,
        "top_color": 0,
        "bottom_color": 6,
        "low3": 6
      },
      {
        "val": 7,
        "full": false,
        "half": false,
        "tunnel": false,
        "top_color": 0,
        "bottom_color": 7,
        "low3": 7
      },
      null,
      null
    ],
    [
      null,
      null,
      {
        "val": 11,
        "full": false,
        "half": false,
        "tunnel": false,
        "top_color": 0,
        "bottom_color": 11,
        "low3": 3
      },
      {
        "val": 7,
        "full": false,
        "half": false,
        "tunnel": false,
        "top_color": 0,
        "bottom_color": 7,
        "low3": 7
      },
      {
        "val": 11,
        "full": false,
        "half": false,
        "tunnel": false,
        "top_color": 0,
        "bottom_color": 11,
        "low3": 3
      },
      null,
      null
    ],
    [
      null,
      null,
      {
        "val": 13,
        "full": false,
        "half": false,
        "tunnel": false,
        "top_color": 0,
        "bottom_color": 13,
        "low3": 5
      },
      {
        "val": 11,
        "full": false,
        "half": false,
        "tunnel": false,
        "top_color": 0,
        "bottom_color": 11,
        "low3": 3
      },
      {
        "val": 13,
        "full": false,
        "half": false,
        "tunnel": false,
        "top_color": 0,
        "bottom_color": 13,
        "low3": 5
      },
      null,
      null
    ],
    [
      null,
      null,
      {
        "val": 14,
        "full": false,
        "half": false,
        "tunnel": false,
        "top_color": 0,
        "bottom_color": 14,
        "low3": 6
      },
      {
        "val": 13,
        "full": false,
        "half": false,
        "tunnel": false,
        "top_color": 0,
        "bottom_color": 13,
        "low3": 5
      },
      {
        "val": 15,
        "full": false,
        "half": false,
        "tunnel": false,
        "top_color": 0,
        "bottom_color": 15,
        "low3": 7
      },
      null,
      null
    ],
    [
      null,
      null,
      {
        "val": 15,
        "full": false,
        "half": false,
        "tunnel": false,
        "top_color": 0,
        "bottom_color": 15,
        "low3": 7
      },
      {
        "val": 14,
        "full": false,
        "half": false,
        "tunnel": false,
        "top_color": 0,
        "bottom_color": 14,
        "low3": 6
      },
      {
        "val": 15,
        "full": false,
        "half": false,
        "tunnel": false,
        "top_color": 0,
        "bottom_color": 15,
        "low3": 7
      },
      null,
      null
    ],
    [
      null,
      null,
      null,
      {
        "val": 15,
        "full": false,
        "half": false,
        "tunnel": false,
        "top_color": 0,
        "bottom_color": 15,
        "low3": 7
      },
      null,
      null,
      null
    ],
    [
      null,
      null,
      null,
      {
        "val": 15,
        "full": false,
        "half": false,
        "tunnel": false,
        "top_color": 0,
        "bottom_color": 15,
        "low3": 7
      },
      null,
      null,
      null
    ],
    [
      null,
      null,
      null,
      {
        "val": 15,
        "full": false,
        "half": false,
        "tunnel": false,
        "top_color": 0,
        "bottom_color": 15,
        "low3": 7
      },
      null,
      null,
      null
    ],
    [
      null,
      null,
      null,
      {
        "val": 12,
        "full": false,
        "half": false,
        "tunnel": false,
        "top_color": 0,
        "bottom_color": 12,
        "low3": 4
      },
      null,
      null,
      null
    ],
    [
      null,
      null,
      null,
      {
        "val": 15,
        "full": false,
        "half": false,
        "tunnel": false,
        "top_color": 0,
        "bottom_color": 15,
        "low3": 7
      },
      null,
      null,
      null
    ],
    [
      null,
      null,
      null,
      {
        "val": 15,
        "full": false,
        "half": false,
        "tunnel": false,
        "top_color": 0,
        "bottom_color": 15,
        "low3": 7
      },
      null,
      null,
      null
    ],
    [
      null,
      null,
      null,
      {
        "val": 12,
        "full": false,
        "half": false,
        "tunnel": false,
        "top_color": 0,
        "bottom_color": 12,
        "low3": 4
      },
      null,
      null,
      null
    ],
    [
      null,
      null,
      null,
      {
        "val": 15,
        "full": false,
        "half": false,
        "tunnel": false,
        "top_color": 0,
        "bottom_color": 15,
        "low3": 7
      },
      null,
      null,
      null
    ],
    [
      null,
      null,
      null,
      {
        "val": 15,
        "full": false,
        "half": false,
        "tunnel": false,
        "top_color": 0,
        "bottom_color": 15,
        "low3": 7
      },
      null,
      null,
      null
    ],
    [
      null,
      null,
      null,
      {
        "val": 12,
        "full": false,
        "half": false,
        "tunnel": false,
        "top_color": 0,
        "bottom_color": 12,
        "low3": 4
      },
      null,
      null,
      null
    ],
    [
      null,
      null,
      null,
      {
        "val": 15,
        "full": false,
        "half": false,
        "tunnel": false,
        "top_color": 0,
        "bottom_color": 15,
        "low3": 7
      },
      null,
      null,
      null
    ],
    [
      null,
      null,
      null,
      {
        "val": 15,
        "full": false,
        "half": false,
        "tunnel": false,
        "top_color": 0,
        "bottom_color": 15,
        "low3": 7
      },
      null,
      null,
      null
    ],
    [
      null,
      null,
      null,
      {
        "val": 12,
        "full": false,
        "half": false,
        "tunnel": false,
        "top_color": 0,
        "bottom_color": 12,
        "low3": 4
      },
      null,
      null,
      null
    ],
    [
      null,
      null,
      null,
      {
        "val": 15,
        "full": false,
        "half": false,
        "tunnel": false,
        "top_color": 0,
        "bottom_color": 15,
        "low3": 7
      },
      null,
      null,
      null
    ],
    [
      null,
      null,
      null,
      {
        "val": 15,
        "full": false,
        "half": false,
        "tunnel": false,
        "top_color": 0,
        "bottom_color": 15,
        "low3": 7
      },
      null,
      null,
      null
    ],
    [
      null,
      null,
      null,
      {
        "val": 15,
        "full": false,
        "half": false,
        "tunnel": false,
        "top_color": 0,
        "bottom_color": 15,
        "low3": 7
      },
      null,
      null,
      null
    ],
    [
      null,
      null,
      null,
      {
        "val": 15,
        "full": false,
        "half": false,
        "tunnel": false,
        "top_color": 0,
        "bottom_color": 15,
        "low3": 7
      },
      null,
      null,
      null
    ],
    [
      null,
      null,
      null,
      {
        "val": 15,
        "full": false,
        "half": false,
        "tunnel": false,
        "top_color": 0,
        "bottom_color": 15,
        "low3": 7
      },
      null,
      null,
      null
    ],
    [
      null,
      null,
      null,
      {
        "val": 15,
        "full": false,
        "half": false,
        "tunnel": false,
        "top_color": 0,
        "bottom_color": 15,
        "low3": 7
      },
      null,
      null,
      null
    ],
    [
      null,
      null,
      null,
      {
        "val": 15,
        "full": false,
        "half": false,
        "tunnel": false,
        "top_color": 0,
        "bottom_color": 15,
        "low3": 7
      },
      null,
      null,
      null
    ],
    [
      null,
      null,
      null,
      {
        "val": 799,
        "full": false,
        "half": true,
        "tunnel": true,
        "top_color": 1,
        "bottom_color": 15,
        "low3": 7
      },
      null,
      null,
      null
    ],
    [
      null,
      null,
      null,
      {
        "val": 799,
        "full": false,
        "half": true,
        "tunnel": true,
        "top_color": 1,
        "bottom_color": 15,
        "low3": 7
      },
      null,
      null,
      null
    ],
    [
      null,
      null,
      null,
      {
        "val": 799,
        "full": false,
        "half": true,
        "tunnel": true,
        "top_color": 1,
        "bottom_color": 15,
        "low3": 7
      },
      null,
      null,
      null
    ],
    [
      null,
      null,
      null,
      {
        "val": 799,
        "full": false,
        "half": true,
        "tunnel": true,
        "top_color": 1,
        "bottom_color": 15,
        "low3": 7
      },
      null,
      null,
      null
    ],
    [
      null,
      null,
      null,
      {
        "val": 15,
        "full": false,
        "half": false,
        "tunnel": false,
        "top_color": 0,
        "bottom_color": 15,
        "low3": 7
      },
      null,
      null,
      null
    ],
    [
      null,
      null,
      null,
      {
        "val": 15,
        "full": false,
        "half": false,
        "tunnel": false,
        "top_color": 0,
        "bottom_color": 15,
        "low3": 7
      },
      null,
      null,
      null
    ],
    [
      null,
      null,
      null,
      {
        "val": 15,
        "full": false,
        "half": false,
        "tunnel": false,
        "top_color": 0,
        "bottom_color": 15,
        "low3": 7
      },
      null,
      null,
      null
    ],
    [
      null,
      null,
      null,
      {
        "val": 15,
        "full": false,
        "half": false,
        "tunnel": false,
        "top_color": 0,
        "bottom_color": 15,
        "low3": 7
      },
      null,
      null,
      null
    ],
    [
      null,
      null,
      null,
      {
        "val": 15,
        "full": false,
        "half": false,
        "tunnel": false,
        "top_color": 0,
        "bottom_color": 15,
        "low3": 7
      },
      null,
      null,
      null
    ],
    [
      null,
      null,
      null,
      {
        "val": 15,
        "full": false,
        "half": false,
        "tunnel": false,
        "top_color": 0,
        "bottom_color": 15,
        "low3": 7
      },
      null,
      null,
      null
    ],
    [
      null,
      null,
      null,
      {
        "val": 15,
        "full": false,
        "half": false,
        "tunnel": false,
        "top_color": 0,
        "bottom_color": 15,
        "low3": 7
      },
      null,
      null,
      null
    ],
    [
      null,
      null,
      null,
      {
        "val": 271,
        "full": false,
        "half": false,
        "tunnel": true,
        "top_color": 0,
        "bottom_color": 15,
        "low3": 7
      },
      null,
      null,
      null
    ],
    [
      null,
      null,
      null,
      {
        "val": 799,
        "full": false,
        "half": true,
        "tunnel": true,
        "top_color": 1,
        "bottom_color": 15,
        "low3": 7
      },
      null,
      null,
      null
    ],
    [
      null,
      null,
      null,
      {
        "val": 799,
        "full": false,
        "half": true,
        "tunnel": true,
        "top_color": 1,
        "bottom_color": 15,
        "low3": 7
      },
      null,
      null,
      null
    ],
    [
      null,
      null,
      null,
      {
        "val": 799,
        "full": false,
        "half": true,
        "tunnel": true,
        "top_color": 1,
        "bottom_color": 15,
        "low3": 7
      },
      null,
      null,
      null
    ],
    [
      null,
      null,
      null,
      {
        "val": 799,
        "full": false,
        "half": true,
        "tunnel": true,
        "top_color": 1,
        "bottom_color": 15,
        "low3": 7
      },
      null,
      null,
      null
    ],
    [
      null,
      null,
      null,
      {
        "val": 1311,
        "full": true,
        "half": false,
        "tunnel": true,
        "top_color": 1,
        "bottom_color": 15,
        "low3": 7
      },
      null,
      null,
      null
    ],
    [
      null,
      null,
      null,
      {
        "val": 1311,
        "full": true,
        "half": false,
        "tunnel": true,
        "top_color": 1,
        "bottom_color": 15,
        "low3": 7
      },
      null,
      null,
      null
    ],
    [
      null,
      null,
      null,
      {
        "val": 1311,
        "full": true,
        "half": false,
        "tunnel": true,
        "top_color": 1,
        "bottom_color": 15,
        "low3": 7
      },
      null,
      null,
      null
    ],
    [
      null,
      null,
      null,
      {
        "val": 1311,
        "full": true,
        "half": false,
        "tunnel": true,
        "top_color": 1,
        "bottom_color": 15,
        "low3": 7
      },
      null,
      null,
      null
    ],
    [
      null,
      null,
      null,
      {
        "val": 1311,
        "full": true,
        "half": false,
        "tunnel": true,
        "top_color": 1,
        "bottom_color": 15,
        "low3": 7
      },
      null,
      null,
      null
    ],
    [
      null,
      null,
      null,
      {
        "val": 1308,
        "full": true,
        "half": false,
        "tunnel": true,
        "top_color": 1,
        "bottom_color": 12,
        "low3": 4
      },
      null,
      null,
      null
    ],
    [
      null,
      null,
      null,
      {
        "val": 15,
        "full": false,
        "half": false,
        "tunnel": false,
        "top_color": 0,
        "bottom_color": 15,
        "low3": 7
      },
      null,
      null,
      null
    ],
    [
      null,
      null,
      null,
      {
        "val": 15,
        "full": false,
        "half": false,
        "tunnel": false,
        "top_color": 0,
        "bottom_color": 15,
        "low3": 7
      },
      null,
      null,
      null
    ],
    [
      null,
      null,
      null,
      {
        "val": 15,
        "full": false,
        "half": false,
        "tunnel": false,
        "top_color": 0,
        "bottom_color": 15,
        "low3": 7
      },
      null,
      null,
      null
    ],
    [
      null,
      null,
      null,
      {
        "val": 15,
        "full": false,
        "half": false,
        "tunnel": false,
        "top_color": 0,
        "bottom_color": 15,
        "low3": 7
      },
      null,
      null,
      null
    ],
    [
      null,
      null,
      null,
      {
        "val": 15,
        "full": false,
        "half": false,
        "tunnel": false,
        "top_color": 0,
        "bottom_color": 15,
        "low3": 7
      },
      null,
      null,
      null
    ],
    [
      null,
      null,
      null,
      {
        "val": 15,
        "full": false,
        "half": false,
        "tunnel": false,
        "top_color": 0,
        "bottom_color": 15,
        "low3": 7
      },
      null,
      null,
      null
    ],
    [
      null,
      null,
      null,
      {
        "val": 271,
        "full": false,
        "half": false,
        "tunnel": true,
        "top_color": 0,
        "bottom_color": 15,
        "low3": 7
      },
      null,
      null,
      null
    ]
  ]
}